knitropytorch/__init__.py
knitropytorch/main.py
knitropytorch/util.py
knitropytorch/version.py
knitropytorch-0.1.0.dist-info/METADATA
knitropytorch-0.1.0.dist-info/WHEEL
knitropytorch-0.1.0.dist-info/top_level.txt
knitropytorch-0.1.0.dist-info/RECORD
