Metadata-Version: 2.1
Name: knitropytorch
Version: 0.1.0
Summary: Pytorch support for Knitro
Home-page: UNKNOWN
Author: Various Contributors
Author-email: jesseperla@gmail.com
License: MIT
Platform: any
Requires-Python: >=3.7
